ansible_docker_ci/__init__.py
ansible_docker_ci/image/__init__.py
ansible_docker_ci/image/connection/__init__.py
ansible_docker_ci/image/connection/plugin.py
ansible_docker_ci/py.typed
ansible_docker_ci/version.py
ansible_docker_ci-1.0.0.dist-info/LICENSE
ansible_docker_ci-1.0.0.dist-info/WHEEL
ansible_docker_ci-1.0.0.dist-info/METADATA
ansible_docker_ci-1.0.0.dist-info/RECORD
